debugckage/__init__.py
debugckage/dprint.py
debugckage-1.0.dist-info/METADATA
debugckage-1.0.dist-info/WHEEL
debugckage-1.0.dist-info/top_level.txt
debugckage-1.0.dist-info/RECORD
