Metadata-Version: 2.1
Name: debugckage
Version: 1.0
Summary: Functions to help debugging
Home-page: https://github.com/JL31/debugckage
Author: JL31
Author-email: jeplul31@gmail.com
License: WTFPL
Platform: UNKNOWN
Classifier: Programming Language :: Python
